<!-- Created by IBM's XMLGenerator

	numberLevels=6, maxRepeats=3, Random seed=988702246679
	fixedOdds=4, impliedOdds=4, defaultOdds=4
	maxIdRefs=3, maxEntities=3, maxNMTokens=3
	entConfigFile=null, entOdds=1
	isExplicitRoot=false
-->
<!-- Generated by YFilter's DocumentGenerator

 element values,
 occurrences of attributes,
 and attribute values
-->


<nitf baselang="13" change.date="1" change.time="1" id="2" uno="4" version="1">
<head id="3">
<meta content="9" http-equiv="3" name="6"></meta>
<meta content="1"></meta>
<meta content="5" id="2" name="14"></meta>
<tobject tobject.type="13">
<tobject.property></tobject.property>
<tobject.property tobject.property.type="9"></tobject.property>
<tobject.subject tobject.subject.code="9" tobject.subject.detail="4" tobject.subject.matter="15" tobject.subject.refnum="4"></tobject.subject></tobject>
<docdata>
<urgency id="20"></urgency>
<correction id="4" id-string="5" info="12"></correction></docdata>
<pubdata date.publication="20" edition.area="11" edition.name="12" ex-ref="9" id="12" position.section="8" position.sequence="9" type="11"></pubdata>
<pubdata edition.area="18" edition.name="8" ex-ref="14" id="20" issn="1" item-length="19" name="2" number="10" unit-of-measure="11"></pubdata>
<revision-history comment="15" function="9" name="1" norm="10"></revision-history>
<revision-history comment="8" name="18" norm="16"></revision-history></head>
<body class="5" dir="17" id="16" lang="18">
<body.content></body.content>
<body.content id="17">
<p class="17" lang="6" optional-text="18" style="13">1
<location>19</location>
<postaddr>
<addressee>
<person idsrc="4" value="19">8</person>
<care.of>12</care.of></addressee>
<country iso-cc="11">2
<alt-code id="2" idsrc="1" value="1"></alt-code>
<alt-code idsrc="8" value="5"></alt-code></country>
<country iso-cc="15">8
<alt-code idsrc="6" value="2"></alt-code></country>
<region code-source="4" id="19" region-code="14">9
<alt-code idsrc="4" value="6"></alt-code></region></postaddr>
<location>13
<alt-code idsrc="20" value="14"></alt-code>
<state state-code="8">19
<alt-code idsrc="17" value="13"></alt-code></state></location></p>
<hr src="19"></hr></body.content>
<body.content>
<table align="17" cellpadding="16" class="8" cols="9" frame="18" id="18" rules="8" table.fmt="10" table.inst="18" tabletype="16" width="19">
<col align="7" char="18" id="14" span="7"></col>
<tfoot align="19" char="16" charoff="14" dir="15" lang="1" style="18">
<tr charoff="3" dir="1" style="19" valign="10">
<td align="14" axes="18" charoff="10" lang="1" nowrap="4" rowspan="10" style="19">9</td>
<td axes="10" char="8" charoff="16" nowrap="5" rowspan="4" valign="1">14</td>
<td char="11" charoff="18" lang="16" nowrap="6" rowspan="5" valign="11">5</td></tr>
<tr align="10" char="18" charoff="6" dir="11" style="6">
<td align="18" axes="11" char="9" charoff="3" lang="5" nowrap="19" valign="9">12</td>
<th align="7" char="6" charoff="14" class="2" colspan="7" dir="7" lang="16" rowspan="17">1</th>
<td char="3" charoff="11" colspan="8" lang="3" nowrap="16" rowspan="3" valign="4">18</td></tr>
<tr char="11" dir="18" style="9">
<th axis="1" char="17" charoff="2" class="7" lang="19" rowspan="19">6</th>
<th align="3" axis="4" char="18" charoff="10" class="16" colspan="16" dir="2" rowspan="1" valign="4">10</th></tr></tfoot>
<tbody char="9" dir="2" valign="12">
<tr charoff="15" dir="19" style="18">
<td axes="18" char="5" charoff="1" rowspan="13" style="3" valign="18">4</td></tr>
<tr char="3" dir="15" lang="6" style="4">
<td axes="5" char="8" charoff="11" lang="6" nowrap="1" valign="12">4</td>
<th colspan="4" lang="10" rowspan="11">19</th>
<th align="15" axes="11" axis="2" charoff="10" class="2" colspan="1" lang="8" rowspan="6">15</th></tr>
<tr char="2" charoff="5" dir="12" style="1">
<th align="8" charoff="14" class="20" colspan="9" lang="17" rowspan="19">15</th>
<th align="3" axis="15" charoff="4" class="10" colspan="1" lang="17" nowrap="3" rowspan="18">19</th></tr></tbody>
<tbody char="10" dir="3" lang="8">
<tr charoff="1" dir="13" id="10" valign="4">
<th align="15" charoff="3" class="9" lang="16" rowspan="12" valign="13">4</th>
<th charoff="5" class="11" colspan="18" dir="17" rowspan="3" valign="1">7</th></tr>
<tr char="11" charoff="13" dir="12" style="20" valign="8">
<th align="15" char="14" charoff="12" class="15" dir="18" lang="15" rowspan="18">1</th></tr></tbody>
<tbody align="6" char="2" lang="3" style="1">
<tr align="12" charoff="13" dir="6" lang="6">
<td charoff="10" lang="17" nowrap="6" rowspan="3">12</td></tr>
<tr dir="12" lang="4" style="6" valign="19">
<td align="13" axes="4" char="15" colspan="2" lang="11" nowrap="9" rowspan="9" valign="14">3</td>
<td axes="13" axis="4" char="17" charoff="19" colspan="4" lang="15" rowspan="18" valign="8">1</td>
<td axes="18" axis="9" charoff="4" id="8" lang="20" nowrap="8" style="12" valign="6">17</td></tr></tbody></table></body.content>
<body.end>
<tagline id="12" type="15">20
<pronounce guide="5">12
<lang lang="12">6
<lang id="4" lang="14" style="6">19</lang>
<object.title class="6" id="18" idsrc="20" lang="18" value="19">20</object.title></lang>
<function idsrc="14" value="11">2</function></pronounce></tagline>
<bibliography>12</bibliography></body.end></body>
</nitf>